{
  "gitSyncId": "69973bfe4e186c017ca07237_fee83633-89be-46cd-bd23-87121069b3e2",
  "id": "Main_jsActions.updateItem",
  "pluginId": "js-plugin",
  "pluginType": "JS",
  "unpublishedAction": {
    "actionConfiguration": {
      "encodeParamsToggle": true,
      "jsArguments": [
        {
          "name": "action"
        },
        {
          "name": "query"
        },
        {
          "name": "data"
        },
        {
          "name": "refresh",
          "value": "{{false}}"
        }
      ],
      "paginationType": "NONE",
      "timeoutInMillisecond": 10000
    },
    "collectionId": "Main_jsActions",
    "confirmBeforeExecute": false,
    "datasource": {
      "isAutoGenerated": false,
      "name": "UNUSED_DATASOURCE",
      "pluginId": "js-plugin"
    },
    "dynamicBindingPathList": [
      {
        "key": "body"
      }
    ],
    "fullyQualifiedName": "jsActions.updateItem",
    "name": "updateItem",
    "pageId": "Main",
    "runBehaviour": "MANUAL",
    "userSetOnLoad": false
  }
}