{
  "gitSyncId": "69bda4409660aa3a71f7bf8b_0bff5244-31a5-45b4-9913-6b0c2254af55",
  "id": "init_jsInit.normalizeLocations",
  "pluginId": "js-plugin",
  "pluginType": "JS",
  "unpublishedAction": {
    "actionConfiguration": {
      "encodeParamsToggle": true,
      "jsArguments": [
        {
          "name": "rows"
        }
      ],
      "paginationType": "NONE",
      "timeoutInMillisecond": 10000
    },
    "collectionId": "init_jsInit",
    "confirmBeforeExecute": false,
    "datasource": {
      "isAutoGenerated": false,
      "name": "UNUSED_DATASOURCE",
      "pluginId": "js-plugin"
    },
    "dynamicBindingPathList": [
      {
        "key": "body"
      }
    ],
    "fullyQualifiedName": "jsInit.normalizeLocations",
    "name": "normalizeLocations",
    "pageId": "init",
    "runBehaviour": "MANUAL",
    "userSetOnLoad": false
  }
}